chag/__init__.py
chag/changelog.py
chag/git.py
chag/main.py
chag-0.5.0.dist-info/DESCRIPTION.rst
chag-0.5.0.dist-info/entry_points.txt
chag-0.5.0.dist-info/METADATA
chag-0.5.0.dist-info/metadata.json
chag-0.5.0.dist-info/RECORD
chag-0.5.0.dist-info/top_level.txt
chag-0.5.0.dist-info/WHEEL
