Metadata-Version: 2.0
Name: chag
Version: 0.5.0
Summary: Parses changelog files and helps with changelog workflows
Home-page: https://github.com/mtdowling/chag
Author: Michael Dowling
Author-email: mtdowling@gmail.com
License: MIT
Keywords: changelog
Platform: UNKNOWN
Classifier: Development Status :: 3 - Alpha
Classifier: License :: OSI Approved :: MIT License
Classifier: Programming Language :: Python :: 2.6
Classifier: Programming Language :: Python :: 2.7
Classifier: Programming Language :: Python :: 3.3
Requires-Dist: click (>=3,<4)
